[
    {
        "name": "Abdulbasit Abdulsamad",
        "url": "https:\/\/radio.mp3islam.com\/listen\/abdulbasit\/radio.mp3",
        "country": "Curacao",
        "countrycode": "CW",
        "state": "",
        "tags": "",
        "bitrate": 192,
        "codec": "MP3",
        "language": "arabic",
        "favicon": "null"
    },
    {
        "name": "Abdulbasit Abdulsamad",
        "url": "https:\/\/radio.mp3islam.com\/listen\/abdulbasit\/radio.mp3",
        "country": "Curacao",
        "countrycode": "CW",
        "state": "",
        "tags": "",
        "bitrate": 192,
        "codec": "MP3",
        "language": "arabic",
        "favicon": "null"
    },
    {
        "name": "DIRECT 92.1FM",
        "url": "https:\/\/s9.voscast.com:7369\/921fm",
        "country": "Curacao",
        "countrycode": "CW",
        "state": "",
        "tags": "",
        "bitrate": 192,
        "codec": "MP3",
        "language": "",
        "favicon": "https:\/\/directmediacuracao.com\/images\/logo-dmc.png"
    },
    {
        "name": "Direct Life 92.1 FM",
        "url": "https:\/\/s9.voscast.com:7369\/921fm",
        "country": "Curacao",
        "countrycode": "CW",
        "state": "",
        "tags": "",
        "bitrate": 192,
        "codec": "MP3",
        "language": "",
        "favicon": "https:\/\/directmediacuracao.com\/images\/logo-dmc.png"
    },
    {
        "name": "Dolfijn FM 97.3",
        "url": "http:\/\/radiostreamfm.com:8130\/radio.mp3",
        "country": "Curacao",
        "countrycode": "CW",
        "state": "",
        "tags": "euro,hits,music,pop,top 40",
        "bitrate": 128,
        "codec": "MP3",
        "language": "spanish,willemstad",
        "favicon": "null"
    },
    {
        "name": "Dolfijn FM Classic 80's 90's",
        "url": "http:\/\/radiostreamfm.com:8120\/radio.mp3",
        "country": "Curacao",
        "countrycode": "CW",
        "state": "",
        "tags": "80s,90s,classics,pop,top40",
        "bitrate": 112,
        "codec": "MP3",
        "language": "spanish,willemstad",
        "favicon": "https:\/\/dolfijngo.com\/wp-content\/uploads\/2022\/06\/cropped-fm-logo-1-180x180.png"
    },
    {
        "name": "Easy 97.9 FM",
        "url": "http:\/\/64.150.176.42:8011\/live",
        "country": "Curacao",
        "countrycode": "CW",
        "state": "",
        "tags": "",
        "bitrate": 128,
        "codec": "MP3",
        "language": "",
        "favicon": ""
    },
    {
        "name": "Easy FM 79.9",
        "url": "http:\/\/64.150.176.42:8011\/live",
        "country": "Curacao",
        "countrycode": "CW",
        "state": "Curaçao",
        "tags": "",
        "bitrate": 128,
        "codec": "MP3",
        "language": "",
        "favicon": ""
    },
    {
        "name": "HITradio 915 Curacao",
        "url": "http:\/\/stream.paradisefm.cw\/HITradio915",
        "country": "Curacao",
        "countrycode": "CW",
        "state": "",
        "tags": "dance,music,pop,willemstad",
        "bitrate": 192,
        "codec": "MP3",
        "language": "willemstad",
        "favicon": "https:\/\/firebasestorage.googleapis.com\/v0\/b\/radiogalaxy-580f4.appspot.com\/o\/images%2FIMG_20240809_131957009.jpg?alt=media&token=94a543cd-b615-42d6-9650-f01cbb525ec3"
    },
    {
        "name": "Joce production fm",
        "url": "http:\/\/stream-179.zeno.fm\/hp4bpr101ehvv?zt=eyJhbGciOiJIUzI1NiJ9.eyJzdHJlYW0iOiJocDRicHIxMDFlaHZ2IiwiaG9zdCI6InN0cmVhbS0xNzkuemVuby5mbSIsInRtIjpmYWxzZSwicnR0bCI6NSwianRpIjoiWlVNcWxQMUZUbnVpLUgtbFpnVGYydyIsImlhdCI6MTc2NTU4MTMwMCwiZXhwIjoxNzY1NTgxMzYwfQ.uhqvEJGgNd9CaMC_KtoI-3N1awVN0BW5vOpZsTVLOE8",
        "country": "Curacao",
        "countrycode": "CW",
        "state": "",
        "tags": "dance,misc,pop,variety",
        "bitrate": 0,
        "codec": "MP3",
        "language": "dutch,willemstad",
        "favicon": "null"
    },
    {
        "name": "Paradise FM 00's & 10's",
        "url": "https:\/\/stream.paradisefm.cw\/00s10s",
        "country": "Curacao",
        "countrycode": "CW",
        "state": "",
        "tags": "00s,10s,music,pop",
        "bitrate": 192,
        "codec": "MP3",
        "language": "willemstad",
        "favicon": "https:\/\/firebasestorage.googleapis.com\/v0\/b\/radiogalaxy-580f4.appspot.com\/o\/images%2FIMG_20240830_090036010.jpg?alt=media&token=a1458f19-fb94-4f54-85e6-449b151630b4"
    },
    {
        "name": "Paradise FM 103.1 Curacao",
        "url": "http:\/\/stream.paradisefm.cw\/ParadiseFM",
        "country": "Curacao",
        "countrycode": "CW",
        "state": "",
        "tags": "music,pop,soft,willemstad",
        "bitrate": 192,
        "codec": "MP3",
        "language": "willemstad",
        "favicon": "https:\/\/firebasestorage.googleapis.com\/v0\/b\/radiogalaxy-580f4.appspot.com\/o\/images%2FIMG_20240809_131655662.jpg?alt=media&token=3b0fd44f-02ec-483e-b0c5-2842e00d4ea0"
    },
    {
        "name": "Paradise FM 60s & 70s",
        "url": "https:\/\/stream.paradisefm.cw\/60s70s",
        "country": "Curacao",
        "countrycode": "CW",
        "state": "",
        "tags": "60s,70s,music,pop",
        "bitrate": 192,
        "codec": "MP3",
        "language": "willemstad",
        "favicon": "https:\/\/firebasestorage.googleapis.com\/v0\/b\/radiogalaxy-580f4.appspot.com\/o\/images%2FIMG_20240830_085815429.jpg?alt=media&token=96ee0b32-9993-4842-916d-450162276bce"
    },
    {
        "name": "Paradise FM 80's & 90's",
        "url": "https:\/\/stream.paradisefm.cw\/80s90s",
        "country": "Curacao",
        "countrycode": "CW",
        "state": "",
        "tags": "80s,90s,music,pop",
        "bitrate": 192,
        "codec": "MP3",
        "language": "willemstad",
        "favicon": "https:\/\/firebasestorage.googleapis.com\/v0\/b\/radiogalaxy-580f4.appspot.com\/o\/images%2FIMG_20240830_085927930.jpg?alt=media&token=c3f2d6dd-6706-436b-bae6-57807357228c"
    },
    {
        "name": "Paradise FM Disco Inferno",
        "url": "https:\/\/stream.paradisefm.cw\/ParadiseDiscoInferno",
        "country": "Curacao",
        "countrycode": "CW",
        "state": "",
        "tags": "disco,inferno,music,pop",
        "bitrate": 192,
        "codec": "MP3",
        "language": "willemstad",
        "favicon": "https:\/\/firebasestorage.googleapis.com\/v0\/b\/radiogalaxy-580f4.appspot.com\/o\/images%2FIMG_20240830_090259478.jpg?alt=media&token=d7b6447d-0f85-4983-97c1-31b02344c9da"
    },
    {
        "name": "Paradise FM Latin",
        "url": "https:\/\/stream.paradisefm.cw\/ParadiseLatin",
        "country": "Curacao",
        "countrycode": "CW",
        "state": "",
        "tags": "latin,music,pop",
        "bitrate": 192,
        "codec": "MP3",
        "language": "willemstad",
        "favicon": "https:\/\/firebasestorage.googleapis.com\/v0\/b\/radiogalaxy-580f4.appspot.com\/o\/images%2FIMG_20240830_090405154.jpg?alt=media&token=437e3ee6-845b-43b1-9b35-1b717b5dcb09"
    },
    {
        "name": "Paradise FM Nonstop",
        "url": "https:\/\/stream.paradisefm.cw\/ParadiseNonstop",
        "country": "Curacao",
        "countrycode": "CW",
        "state": "",
        "tags": "classic,music,pop",
        "bitrate": 192,
        "codec": "MP3",
        "language": "willemstad",
        "favicon": "https:\/\/firebasestorage.googleapis.com\/v0\/b\/radiogalaxy-580f4.appspot.com\/o\/images%2FIMG_20240830_090125214.jpg?alt=media&token=7c3b8daa-ae45-4725-9104-bf8a716c17c4"
    },
    {
        "name": "Radio 94 Korsou - 94.5 Willemstad",
        "url": "http:\/\/162.243.94.61:8028\/;stream.mp3",
        "country": "Curacao",
        "countrycode": "CW",
        "state": "",
        "tags": "latin music,pop,willemstad",
        "bitrate": 100,
        "codec": "MP3",
        "language": "papiamentu",
        "favicon": ""
    },
    {
        "name": "Radio Active 104.5 FM",
        "url": "https:\/\/kadushi.westream.cloud\/listen\/radioactive\/RadioActive",
        "country": "Curacao",
        "countrycode": "CW",
        "state": "",
        "tags": "music,pop,talk,variety",
        "bitrate": 96,
        "codec": "MP3",
        "language": "willemstad",
        "favicon": "https:\/\/firebasestorage.googleapis.com\/v0\/b\/radiogalaxy-580f4.appspot.com\/o\/images%2FIMG_20240830_085450771.jpg?alt=media&token=7c8e0059-545b-4ba7-b15c-292e966d3e5f"
    },
    {
        "name": "Radio Deltha 92.7 FM",
        "url": "https:\/\/kadushi.westream.cloud\/listen\/delta\/live",
        "country": "Curacao",
        "countrycode": "CW",
        "state": "",
        "tags": "music,pop,various,world",
        "bitrate": 0,
        "codec": "MP3",
        "language": "willemstad",
        "favicon": "https:\/\/firebasestorage.googleapis.com\/v0\/b\/radiogalaxy-580f4.appspot.com\/o\/images%2FIMG_20240830_090816288.jpg?alt=media&token=60607aaa-889a-4415-aa2e-9d0e4442f84c"
    },
    {
        "name": "Radio Direct 107.1FM",
        "url": "https:\/\/edge1.direct107.com\/;?type=http&nocache=28",
        "country": "Curacao",
        "countrycode": "CW",
        "state": "",
        "tags": "",
        "bitrate": 192,
        "codec": "MP3",
        "language": "",
        "favicon": ""
    },
    {
        "name": "Radio Direct 107.1FM",
        "url": "https:\/\/edge1.direct107.com\/;?type=http&nocache=28",
        "country": "Curacao",
        "countrycode": "CW",
        "state": "",
        "tags": "",
        "bitrate": 192,
        "codec": "MP3",
        "language": "",
        "favicon": ""
    },
    {
        "name": "Radio Hoyer 1 101.9",
        "url": "https:\/\/s1.voscast.com:10487\/live",
        "country": "Curacao",
        "countrycode": "CW",
        "state": "",
        "tags": "music,pop,top40,world",
        "bitrate": 64,
        "codec": "MP3",
        "language": "willemstad",
        "favicon": "https:\/\/firebasestorage.googleapis.com\/v0\/b\/radiogalaxy-580f4.appspot.com\/o\/images%2FIMG_20240830_091231820.jpg?alt=media&token=398d9154-8593-41ba-b77c-922cd20e590f"
    },
    {
        "name": "Radio Hoyer 2 105.1",
        "url": "https:\/\/s1.voscast.com:10489\/live",
        "country": "Curacao",
        "countrycode": "CW",
        "state": "",
        "tags": "music,pop,top40,various",
        "bitrate": 64,
        "codec": "MP3",
        "language": "willemstad",
        "favicon": "https:\/\/firebasestorage.googleapis.com\/v0\/b\/radiogalaxy-580f4.appspot.com\/o\/images%2FIMG_20240830_091429905.jpg?alt=media&token=ea408416-6244-4787-840b-e4b56ec881c2"
    },
    {
        "name": "Radio Krioyo 89.7 FM",
        "url": "https:\/\/radios.wakenext.com\/hls\/radio_kriyoyo_2\/live.m3u8",
        "country": "Curacao",
        "countrycode": "CW",
        "state": "",
        "tags": "",
        "bitrate": 52,
        "codec": "AAC",
        "language": "",
        "favicon": ""
    },
    {
        "name": "Radio Mas",
        "url": "https:\/\/radios.wakenext.com\/hls\/radio_mas99\/live.m3u8",
        "country": "Curacao",
        "countrycode": "CW",
        "state": "",
        "tags": "",
        "bitrate": 52,
        "codec": "AAC",
        "language": "",
        "favicon": "https:\/\/www.mas99.cw\/wp-content\/uploads\/2024\/04\/cropped-Logo-Mas99-512-1.png"
    },
    {
        "name": "Radio Mas 99.7 FM",
        "url": "https:\/\/kadushi.westream.cloud\/listen\/mas99\/live",
        "country": "Curacao",
        "countrycode": "CW",
        "state": "",
        "tags": "music,pop,top40,world",
        "bitrate": 128,
        "codec": "MP3",
        "language": "willemstad",
        "favicon": "https:\/\/www.mas99.cw\/favicon.ico"
    },
    {
        "name": "Radio Resurekshon i Bida",
        "url": "https:\/\/mediaserv38.live-streams.nl:18011\/autodj",
        "country": "Curacao",
        "countrycode": "CW",
        "state": "Kaya Chikucha 22, Willemstad, Koralspecht, Curaçao",
        "tags": "gospel",
        "bitrate": 128,
        "codec": "MP3",
        "language": "papiamentu",
        "favicon": ""
    },
    {
        "name": "Ritmo Antiyano FM",
        "url": "https:\/\/ec6.yesstreaming.net:3105\/stream",
        "country": "Curacao",
        "countrycode": "CW",
        "state": "",
        "tags": "dance,pop,top 40,variety",
        "bitrate": 128,
        "codec": "MP3",
        "language": "dutch,willemstad",
        "favicon": "null"
    }
]